pymir3-cl.py
setup.cfg
setup.py
mir3/__init__.py
mir3/module.py
mir3/subparser.py
mir3/data/__init__.py
mir3/data/base_object.py
mir3/data/blank.py
mir3/data/data_object.py
mir3/data/evaluation.py
mir3/data/feature_matrix.py
mir3/data/feature_track.py
mir3/data/linear_decomposition.py
mir3/data/metadata.py
mir3/data/note.py
mir3/data/score.py
mir3/data/self_similarity_matrix.py
mir3/data/spectrogram.py
mir3/lib/__init__.py
mir3/lib/distances.py
mir3/lib/feature_selection.py
mir3/lib/knn.py
mir3/lib/median_filtering.py
mir3/lib/naive_bayes.py
mir3/lib/pca.py
mir3/lib/periodicity.py
mir3/lib/self_similarity.py
mir3/lib/midi/DataTypeConverters.py
mir3/lib/midi/EventDispatcher.py
mir3/lib/midi/MidiFileParser.py
mir3/lib/midi/MidiInFile.py
mir3/lib/midi/MidiInStream.py
mir3/lib/midi/MidiOutFile.py
mir3/lib/midi/MidiOutStream.py
mir3/lib/midi/MidiToText.py
mir3/lib/midi/RawInstreamFile.py
mir3/lib/midi/RawOutstreamFile.py
mir3/lib/midi/__init__.py
mir3/lib/midi/constants.py
mir3/lib/midi/example_mimimal_type0.py
mir3/lib/midi/example_print_channel_0.py
mir3/lib/midi/example_print_events.py
mir3/lib/midi/example_print_file.py
mir3/lib/midi/example_transpose_octave.py
mir3/lib/midi/midi_test.py
mir3/lib/mir/__init__.py
mir3/lib/mir/features.py
mir3/lib/mir/mfcc.py
mir3/lib/mir/midifeatures.py
mir3/lib/mir/tdom_features.py
mir3/modules/__init__.py
mir3/modules/classification_submodule.py
mir3/modules/evaluation_submodule.py
mir3/modules/features_submodule.py
mir3/modules/info_submodule.py
mir3/modules/recommendation_submodule.py
mir3/modules/structure_submodule.py
mir3/modules/supervised_submodule.py
mir3/modules/symbolic_submodule.py
mir3/modules/tool_submodule.py
mir3/modules/unsupervised_submodule.py
mir3/modules/classification/__init__.py
mir3/modules/classification/featurematrix.py
mir3/modules/evaluation/__init__.py
mir3/modules/evaluation/mirex_framewise.py
mir3/modules/evaluation/mirex_symbolic.py
mir3/modules/features/__init__.py
mir3/modules/features/centroid.py
pymir3.egg-info/PKG-INFO
pymir3.egg-info/SOURCES.txt
pymir3.egg-info/dependency_links.txt
pymir3.egg-info/top_level.txt