Metadata-Version: 1.0
Name: pymir3
Version: 1.0
Summary: Python utilities for Music Information Retrieval applications
Home-page: https://github.com/pymir3/pymir3
Author: Tiago F. Tavares, Conrado Miranda
Author-email: tavares@dca.fee.unicamp.br
License: MIT License
Keywords: music information retrieval,mir,prototyping
Platform: UNKNOWN
